[
  {
    "species_name": "Gothorita",
    "variant_name": "Gothorita",
    "types": [
      "Psychic"
    ],
    "base_stats": {
      "hp": 60,
      "attack": 45,
      "defense": 70,
      "speed": 55,
      "special_attack": 75,
      "special_defense": 85
    },
    "dex_entry": {
      "national_dex_num": 575,
      "height": 0.7,
      "weight": 18.0,
      "color": "INVALID",
      "shape": "INVALID",
      "kind": "Manipulate Pokémon",
      "flavor_text": "On nights when the stars shine, this Pokémon’s psychic power is at its strongest. It’s unknown just what link Gothorita has to the greater universe.",
      "abilities": [
        "Frisk",
        "Competitive"
      ],
      "hidden_abilities": [
        "Shadow Tag"
      ],
      "regional_dex_nums": {
        "bw": 81,
        "b2w2": 137,
        "xy_mountain": 127,
        "swsh": 268
      }
    },
    "training_info": {
      "leveling_rate": "MediumSlow",
      "base_exp_yield": 137,
      "effort_points": {
        "hp": 0,
        "attack": 0,
        "defense": 0,
        "speed": 0,
        "special_attack": 0,
        "special_defense": 2
      },
      "catch_rate": 100,
      "base_friendship": 70
    },
    "breeding_info": {
      "egg_groups": [
        "Humanlike"
      ],
      "male_rate": 25.0,
      "steps_to_hatch_lower": 4884,
      "steps_to_hatch_upper": 5140,
      "egg_cycles": 20
    },
    "move_info": {
      "learned_moves": [
        [
          1,
          "Confusion"
        ],
        [
          1,
          "Play Nice"
        ],
        [
          1,
          "Pound"
        ],
        [
          1,
          "Tickle"
        ],
        [
          3,
          "Confusion"
        ],
        [
          7,
          "Tickle"
        ],
        [
          10,
          "Fake Tears"
        ],
        [
          14,
          "Double Slap"
        ],
        [
          16,
          "Psybeam"
        ],
        [
          19,
          "Embargo"
        ],
        [
          24,
          "Feint Attack"
        ],
        [
          25,
          "Psyshock"
        ],
        [
          28,
          "Flatter"
        ],
        [
          31,
          "Future Sight"
        ],
        [
          34,
          "Heal Block"
        ],
        [
          39,
          "Psychic"
        ],
        [
          43,
          "Telekinesis"
        ],
        [
          50,
          "Charm"
        ],
        [
          53,
          "Magic Room"
        ]
      ],
      "tm_moves": [
        [
          3,
          "Psyshock"
        ],
        [
          4,
          "Calm Mind"
        ],
        [
          6,
          "Toxic"
        ],
        [
          10,
          "Hidden Power"
        ],
        [
          12,
          "Taunt"
        ],
        [
          16,
          "Light Screen"
        ],
        [
          17,
          "Protect"
        ],
        [
          18,
          "Rain Dance"
        ],
        [
          20,
          "Safeguard"
        ],
        [
          21,
          "Frustration"
        ],
        [
          24,
          "Thunderbolt"
        ],
        [
          27,
          "Return"
        ],
        [
          29,
          "Psychic"
        ],
        [
          30,
          "Shadow Ball"
        ],
        [
          32,
          "Double Team"
        ],
        [
          33,
          "Reflect"
        ],
        [
          39,
          "Rock Tomb"
        ],
        [
          41,
          "Torment"
        ],
        [
          42,
          "Facade"
        ],
        [
          44,
          "Rest"
        ],
        [
          45,
          "Attract"
        ],
        [
          46,
          "Thief"
        ],
        [
          48,
          "Round"
        ],
        [
          53,
          "Energy Ball"
        ],
        [
          56,
          "Fling"
        ],
        [
          57,
          "Charge Beam"
        ],
        [
          63,
          "Embargo"
        ],
        [
          66,
          "Payback"
        ],
        [
          73,
          "Thunder Wave"
        ],
        [
          77,
          "Psych Up"
        ],
        [
          80,
          "Rock Slide"
        ],
        [
          85,
          "Dream Eater"
        ],
        [
          86,
          "Grass Knot"
        ],
        [
          87,
          "Swagger"
        ],
        [
          88,
          "Sleep Talk"
        ],
        [
          90,
          "Substitute"
        ],
        [
          92,
          "Trick Room"
        ],
        [
          97,
          "Dark Pulse"
        ],
        [
          100,
          "Confide"
        ]
      ],
      "tr_moves": [],
      "evolution_moves": [],
      "egg_moves": [
        "Captivate",
        "Dark Pulse",
        "Heal Pulse",
        "Mean Look",
        "Miracle Eye",
        "Mirror Coat",
        "Uproar"
      ],
      "tutor_moves": [
        "Ally Switch",
        "Covet",
        "Foul Play",
        "Gravity",
        "Heal Bell",
        "Helping Hand",
        "Magic Coat",
        "Magic Room",
        "Recycle",
        "Role Play",
        "Shock Wave",
        "Signal Beam",
        "Skill Swap",
        "Snatch",
        "Snore",
        "Telekinesis",
        "Trick",
        "Uproar",
        "Zen Headbutt"
      ],
      "transfer_moves": [
        "Flash",
        "Secret Power"
      ]
    }
  }
]