[
  {
    "species_name": "Staravia",
    "variant_name": "Staravia",
    "types": [
      "Normal",
      "Flying"
    ],
    "base_stats": {
      "hp": 55,
      "attack": 75,
      "defense": 50,
      "speed": 80,
      "special_attack": 40,
      "special_defense": 40
    },
    "dex_entry": {
      "national_dex_num": 397,
      "height": 0.6,
      "weight": 15.5,
      "color": "INVALID",
      "shape": "INVALID",
      "kind": "Starling Pokémon",
      "flavor_text": "It lives in forests and fields. Squabbles over territory occur when flocks collide.",
      "abilities": [
        "Intimidate"
      ],
      "hidden_abilities": [
        "Reckless"
      ],
      "regional_dex_nums": {
        "dp": 11,
        "plat": 11,
        "xy_coastal": 100
      }
    },
    "training_info": {
      "leveling_rate": "MediumSlow",
      "base_exp_yield": 119,
      "effort_points": {
        "hp": 0,
        "attack": 0,
        "defense": 0,
        "speed": 2,
        "special_attack": 0,
        "special_defense": 0
      },
      "catch_rate": 120,
      "base_friendship": 70
    },
    "breeding_info": {
      "egg_groups": [
        "Flying"
      ],
      "male_rate": 50.0,
      "steps_to_hatch_lower": 3599,
      "steps_to_hatch_upper": 3855,
      "egg_cycles": 15
    },
    "move_info": {
      "learned_moves": [
        [
          1,
          "Growl"
        ],
        [
          1,
          "Quick Attack"
        ],
        [
          1,
          "Tackle"
        ],
        [
          5,
          "Quick Attack"
        ],
        [
          9,
          "Wing Attack"
        ],
        [
          13,
          "Double Team"
        ],
        [
          18,
          "Endeavor"
        ],
        [
          23,
          "Whirlwind"
        ],
        [
          28,
          "Aerial Ace"
        ],
        [
          33,
          "Take Down"
        ],
        [
          38,
          "Agility"
        ],
        [
          43,
          "Brave Bird"
        ],
        [
          48,
          "Final Gambit"
        ]
      ],
      "tm_moves": [
        [
          1,
          "Work Up"
        ],
        [
          6,
          "Toxic"
        ],
        [
          10,
          "Hidden Power"
        ],
        [
          11,
          "Sunny Day"
        ],
        [
          17,
          "Protect"
        ],
        [
          18,
          "Rain Dance"
        ],
        [
          19,
          "Roost"
        ],
        [
          21,
          "Frustration"
        ],
        [
          27,
          "Return"
        ],
        [
          32,
          "Double Team"
        ],
        [
          40,
          "Aerial Ace"
        ],
        [
          42,
          "Facade"
        ],
        [
          44,
          "Rest"
        ],
        [
          45,
          "Attract"
        ],
        [
          46,
          "Thief"
        ],
        [
          48,
          "Round"
        ],
        [
          49,
          "Echoed Voice"
        ],
        [
          51,
          "Steel Wing"
        ],
        [
          76,
          "Fly"
        ],
        [
          87,
          "Swagger"
        ],
        [
          88,
          "Sleep Talk"
        ],
        [
          89,
          "U-turn"
        ],
        [
          90,
          "Substitute"
        ],
        [
          100,
          "Confide"
        ]
      ],
      "tr_moves": [],
      "evolution_moves": [],
      "egg_moves": [
        "Astonish",
        "Detect",
        "Double-Edge",
        "Feather Dance",
        "Foresight",
        "Fury Attack",
        "Mirror Move",
        "Pursuit",
        "Revenge",
        "Roost",
        "Sand Attack",
        "Steel Wing",
        "Uproar"
      ],
      "tutor_moves": [
        "Defog",
        "Endeavor",
        "Heat Wave",
        "Snore",
        "Tailwind",
        "Uproar"
      ],
      "transfer_moves": [
        "Air Cutter",
        "Captivate",
        "Endure",
        "Mud-Slap",
        "Natural Gift",
        "Ominous Wind",
        "Pluck",
        "Retaliate",
        "Secret Power",
        "Swift",
        "Twister"
      ]
    }
  }
]